hello/__init__.py
hello/world.py
test/__init__.py
test/test_hello.py
ezcl_py_hello-8.0.0.dist-info/LICENSE
ezcl_py_hello-8.0.0.dist-info/METADATA
ezcl_py_hello-8.0.0.dist-info/WHEEL
ezcl_py_hello-8.0.0.dist-info/entry_points.txt
ezcl_py_hello-8.0.0.dist-info/top_level.txt
ezcl_py_hello-8.0.0.dist-info/RECORD
