Metadata-Version: 2.1
Name: ezcl-py-hello
Version: 8.0.0
Summary: A simple "Hello, World!" package
Home-page: https://github.com/eazycloudlife/ezcl-py-hello
Author: Eazy Cloud Life
Author-email: wazycloudlife@email.com
License: MIT
Classifier: Programming Language :: Python :: 3
Classifier: License :: OSI Approved :: MIT License
Classifier: Operating System :: OS Independent
Requires-Python: >=3.12.4
License-File: LICENSE
